lm_dataformat/__init__.py
lm_dataformat-0.0.20.dist-info/LICENSE
lm_dataformat-0.0.20.dist-info/METADATA
lm_dataformat-0.0.20.dist-info/WHEEL
lm_dataformat-0.0.20.dist-info/top_level.txt
lm_dataformat-0.0.20.dist-info/RECORD
