Metadata-Version: 2.1
Name: lm-dataformat
Version: 0.0.20
Summary: A utility for storing and reading files for LM training.
Home-page: https://github.com/leogao2/lm_dataformat
Author: Leo Gao
Author-email: leogao31@gmail.com
License: UNKNOWN
Platform: UNKNOWN
Requires-Python: >=3.6
Requires-Dist: jsonlines
Requires-Dist: ujson
Requires-Dist: zstandard
